MANIFEST.in
README.md
setup.cfg
setup.py
airflow/__init__.py
airflow/alembic.ini
airflow/configuration.py
airflow/default_login.py
airflow/exceptions.py
airflow/logging_config.py
airflow/plugins_manager.py
airflow/settings.py
airflow/version.py
airflow/_vendor/README
airflow/_vendor/__init__.py
airflow/_vendor/nvd3/LICENSE
airflow/_vendor/nvd3/NVD3Chart.py
airflow/_vendor/nvd3/__init__.py
airflow/_vendor/nvd3/cumulativeLineChart.py
airflow/_vendor/nvd3/discreteBarChart.py
airflow/_vendor/nvd3/ipynb.py
airflow/_vendor/nvd3/lineChart.py
airflow/_vendor/nvd3/linePlusBarChart.py
airflow/_vendor/nvd3/lineWithFocusChart.py
airflow/_vendor/nvd3/multiBarChart.py
airflow/_vendor/nvd3/multiBarHorizontalChart.py
airflow/_vendor/nvd3/pieChart.py
airflow/_vendor/nvd3/scatterChart.py
airflow/_vendor/nvd3/stackedAreaChart.py
airflow/_vendor/nvd3/translator.py
airflow/_vendor/nvd3/templates/base.html
airflow/_vendor/nvd3/templates/content.html
airflow/_vendor/nvd3/templates/cumulativelinechart.html
airflow/_vendor/nvd3/templates/discretebarchart.html
airflow/_vendor/nvd3/templates/linebarwfocuschart.html
airflow/_vendor/nvd3/templates/linechart.html
airflow/_vendor/nvd3/templates/lineplusbarchart.html
airflow/_vendor/nvd3/templates/linewfocuschart.html
airflow/_vendor/nvd3/templates/multibarchart.html
airflow/_vendor/nvd3/templates/multibarcharthorizontal.html
airflow/_vendor/nvd3/templates/page.html
airflow/_vendor/nvd3/templates/piechart.html
airflow/_vendor/nvd3/templates/scatterchart.html
airflow/_vendor/nvd3/templates/stackedareachart.html
airflow/_vendor/slugify/LICENSE
airflow/_vendor/slugify/__init__.py
airflow/_vendor/slugify/slugify.py
airflow/api/__init__.py
airflow/api/auth/__init__.py
airflow/api/auth/backend/__init__.py
airflow/api/auth/backend/default.py
airflow/api/auth/backend/deny_all.py
airflow/api/auth/backend/kerberos_auth.py
airflow/api/client/__init__.py
airflow/api/client/api_client.py
airflow/api/client/json_client.py
airflow/api/client/local_client.py
apache_airflow_arup.egg-info/PKG-INFO
apache_airflow_arup.egg-info/SOURCES.txt
apache_airflow_arup.egg-info/dependency_links.txt
apache_airflow_arup.egg-info/not-zip-safe
apache_airflow_arup.egg-info/requires.txt
apache_airflow_arup.egg-info/top_level.txt
